{
  "needs": {
    "energy": 59.070000000000434,
    "hunger": 10.889999999951263,
    "mood": 100,
    "aura": 69.57949999997915,
    "hygiene": 37.620000000010755
  },
  "emotion": {
    "type": "hype",
    "intensity": 0.8,
    "lastUpdate": 1776132874716
  },
  "routine": {
    "currentAction": "stream_live",
    "startedAt": 1776132818208,
    "duration": 60000,
    "forced": null,
    "lockedUntil": 0
  },
  "world": {
    "location": "pc",
    "isMoving": false
  },
  "user": {
    "isActive": true,
    "lastSeen": 1775958553359
  },
  "inventory": {
    "decor": "small_cactus",
    "outfit": "red_dress"
  },
  "tokens": 0,
  "system": {
    "lastTick": 1776132874716
  }
}