{
  "enabled": false,
  "wakeWords": [
    "sune",
    "kit sune"
  ],
  "wakeWordVariants": [
    "kit",
    "quiti",
    "kite",
    "quite",
    "kiti",
    "kity",
    "sun",
    "tsune",
    "zune",
    "sane",
    "sani",
    "suni",
    "suny",
    "suno"
  ],
  "confirmationMode": "voice",
  "confirmationAudio": "F:/AI/Ai_kit/voz/kit/fala.wav",
  "fallbackAudio": "F:/AI/Ai_kit/voz/kit/bip.wav",
  "continuousListening": true,
  "bypassWakeWordOnNoise": false,
  "passiveCaptureMs": 2200,
  "activeMaxDurationMs": 12000,
  "silenceTimeoutMs": 1000,
  "cooldownMs": 1500,
  "minVoiceDurationMs": 180,
  "ignoreWhileTts": true,
  "stripWakeWordFromCommand": true,
  "debugLogs": true,
  "voiceActivityThreshold": 0.02,
  "activeVoiceThreshold": 0.015,
  "maxInitialSilenceMs": 4000
}